caustic/lexer/__init__.py
caustic/lexer/basic_compiler.py
caustic/lexer/compiler.py
caustic/lexer/grammar.cag
caustic/lexer/nodes.py
caustic/lexer/precompiled_nodes.pkl
caustic/lexer/serialize.py
caustic/lexer/util.py
caustic.lexer-1.3.0.dist-info/LICENSE
caustic.lexer-1.3.0.dist-info/METADATA
caustic.lexer-1.3.0.dist-info/WHEEL
caustic.lexer-1.3.0.dist-info/top_level.txt
caustic.lexer-1.3.0.dist-info/RECORD
