Metadata-Version: 2.1
Name: caustic.lexer
Version: 1.3.0
Summary: Grammar compilation for Caustic
Author: Shae.c32
Project-URL: Homepage, https://codeberg.org/Caustic/CausticLexer
Project-URL: Issues, https://codeberg.org/Caustic/CausticLexer/issues
Keywords: caustic,language,parser,lexer
Classifier: Development Status :: 4 - Beta
Classifier: Intended Audience :: Developers
Classifier: License :: OSI Approved :: Apache Software License
Classifier: Natural Language :: English
Classifier: Programming Language :: Other
Classifier: Topic :: File Formats
Classifier: Topic :: Software Development
Classifier: Topic :: Software Development :: Compilers
Classifier: Topic :: Software Development :: Interpreters
Classifier: Topic :: Software Development :: Pre-processors
Classifier: Topic :: Text Processing
Requires-Python: >=3.12
License-File: LICENSE
Requires-Dist: buffer-matcher >=0.1.1
